CHANGELOG.md
LICENSE.txt
MANIFEST.in
README.md
requirements.txt
setup.cfg
setup.py
dockerwithgitlabsecrets/__init__.py
dockerwithgitlabsecrets/configuration.py
dockerwithgitlabsecrets/entrypoint.py
dockerwithgitlabsecrets/wrapper.py
dockerwithgitlabsecrets.egg-info/PKG-INFO
dockerwithgitlabsecrets.egg-info/SOURCES.txt
dockerwithgitlabsecrets.egg-info/dependency_links.txt
dockerwithgitlabsecrets.egg-info/entry_points.txt
dockerwithgitlabsecrets.egg-info/requires.txt
dockerwithgitlabsecrets.egg-info/top_level.txt
dockerwithgitlabsecrets/tests/__init__.py
dockerwithgitlabsecrets/tests/_common.py
dockerwithgitlabsecrets/tests/test_configuration.py
dockerwithgitlabsecrets/tests/test_entrypoint.py
dockerwithgitlabsecrets/tests/test_wrapper.py