Metadata-Version: 1.0
Name: dockerwithgitlabsecrets
Version: 2.0.0
Summary: Wraps Docker to run with GitLab build variables
Home-page: https://github.com/wtsi-hgi/docker-with-gitlab-secrets
Author: Colin Nolan
Author-email: colin.nolan@sanger.ac.uk
License: MIT
Platform: UNKNOWN
